qvest/__init__.py
qvest/__main__.py
qvest/config_manager.py
qvest/prediction.py
qvest-1.0.1.dist-info/licenses/LICENSE
qvest-1.0.1.dist-info/METADATA
qvest-1.0.1.dist-info/WHEEL
qvest-1.0.1.dist-info/entry_points.txt
qvest-1.0.1.dist-info/top_level.txt
qvest-1.0.1.dist-info/RECORD
