Metadata-Version: 2.4
Name: qvest
Version: 1.0.1
Summary: IBM Quantum-powered portfolio optimization CLI tool
Home-page: https://github.com/Minhal128/qvest
Author: Minhal Rizvi
Author-email: Minhal Rizvi <minhal@example.com>
License: MIT
Project-URL: Homepage, https://github.com/Minhal128/qvest
Project-URL: Bug Reports, https://github.com/Minhal128/qvest/issues
Project-URL: Source, https://github.com/Minhal128/qvest
Keywords: quantum computing,portfolio optimization,IBM Quantum,finance,investment
Classifier: Development Status :: 4 - Beta
Classifier: Intended Audience :: Financial and Insurance Industry
Classifier: Intended Audience :: Science/Research
Classifier: License :: OSI Approved :: MIT License
Classifier: Operating System :: OS Independent
Classifier: Programming Language :: Python :: 3
Classifier: Programming Language :: Python :: 3.8
Classifier: Programming Language :: Python :: 3.9
Classifier: Programming Language :: Python :: 3.10
Classifier: Programming Language :: Python :: 3.11
Classifier: Topic :: Scientific/Engineering :: Physics
Classifier: Topic :: Office/Business :: Financial :: Investment
Requires-Python: >=3.8
License-File: LICENSE
Requires-Dist: numpy>=1.21.0
Requires-Dist: pandas>=1.3.0
Requires-Dist: yfinance>=0.1.87
Requires-Dist: scipy>=1.7.0
Requires-Dist: qiskit>=0.45.0
Requires-Dist: qiskit-ibm-runtime>=0.15.0
Requires-Dist: qiskit-aer>=0.12.0
Requires-Dist: python-dotenv>=0.19.0
Provides-Extra: dev
Requires-Dist: pytest>=6.0.0; extra == "dev"
Requires-Dist: pytest-cov>=2.10.0; extra == "dev"
Requires-Dist: black>=21.0.0; extra == "dev"
Requires-Dist: flake8>=3.8.0; extra == "dev"
Dynamic: author
Dynamic: home-page
Dynamic: license-file
Dynamic: requires-python
